{
	"textures": [
		{
			"image": "arm_uzi.png",
			"format": "RGBA8888",
			"size": {
				"w": 3040,
				"h": 2542
			},
			"scale": 1,
			"frames": [
				{
					"filename": "arm_uzi_003.png",
					"rotated": false,
					"trimmed": true,
					"sourceSize": {
						"w": 1783,
						"h": 575
					},
					"spriteSourceSize": {
						"x": 136,
						"y": 58,
						"w": 1475,
						"h": 507
					},
					"frame": {
						"x": 1,
						"y": 1,
						"w": 1475,
						"h": 507
					},
					"anchor": {
						"x": 0.2232192933258553,
						"y": 0.21739130434782608
					}
				},
				{
					"filename": "arm_uzi_009.png",
					"rotated": false,
					"trimmed": true,
					"sourceSize": {
						"w": 1783,
						"h": 575
					},
					"spriteSourceSize": {
						"x": 171,
						"y": 35,
						"w": 1562,
						"h": 506
					},
					"frame": {
						"x": 1,
						"y": 510,
						"w": 1562,
						"h": 506
					},
					"anchor": {
						"x": 0.23275379,
						"y": 0.1826087
					}
				},
				{
					"filename": "arm_uzi_001.png",
					"rotated": false,
					"trimmed": true,
					"sourceSize": {
						"w": 1783,
						"h": 575
					},
					"spriteSourceSize": {
						"x": 170,
						"y": 36,
						"w": 1560,
						"h": 506
					},
					"frame": {
						"x": 1478,
						"y": 1,
						"w": 1560,
						"h": 506
					},
					"anchor": {
						"x": 0.2338754907459338,
						"y": 0.1791304347826087
					}
				},
				{
					"filename": "arm_uzi_000.png",
					"rotated": false,
					"trimmed": true,
					"sourceSize": {
						"w": 1783,
						"h": 575
					},
					"spriteSourceSize": {
						"x": 186,
						"y": 5,
						"w": 1595,
						"h": 505
					},
					"frame": {
						"x": 1,
						"y": 1018,
						"w": 1595,
						"h": 505
					},
					"anchor": {
						"x": 0.2411665731912507,
						"y": 0.1565217391304348
					}
				},
				{
					"filename": "arm_uzi_006.png",
					"rotated": false,
					"trimmed": true,
					"sourceSize": {
						"w": 1783,
						"h": 575
					},
					"spriteSourceSize": {
						"x": 116,
						"y": 50,
						"w": 1442,
						"h": 507
					},
					"frame": {
						"x": 1565,
						"y": 509,
						"w": 1442,
						"h": 507
					},
					"anchor": {
						"x": 0.21873247335950646,
						"y": 0.21913043478260869
					}
				},
				{
					"filename": "arm_uzi_004.png",
					"rotated": false,
					"trimmed": true,
					"sourceSize": {
						"w": 1783,
						"h": 575
					},
					"spriteSourceSize": {
						"x": 108,
						"y": 47,
						"w": 1441,
						"h": 507
					},
					"frame": {
						"x": 1598,
						"y": 1018,
						"w": 1441,
						"h": 507
					},
					"anchor": {
						"x": 0.2153673583847448,
						"y": 0.20347826086956522
					}
				},
				{
					"filename": "arm_uzi_005.png",
					"rotated": false,
					"trimmed": true,
					"sourceSize": {
						"w": 1783,
						"h": 575
					},
					"spriteSourceSize": {
						"x": 59,
						"y": 28,
						"w": 1441,
						"h": 507
					},
					"frame": {
						"x": 1,
						"y": 1525,
						"w": 1441,
						"h": 507
					},
					"anchor": {
						"x": 0.2047111609646663,
						"y": 0.19304347826086957
					}
				},
				{
					"filename": "arm_uzi_008.png",
					"rotated": false,
					"trimmed": true,
					"sourceSize": {
						"w": 1783,
						"h": 575
					},
					"spriteSourceSize": {
						"x": 155,
						"y": 54,
						"w": 1522,
						"h": 506
					},
					"frame": {
						"x": 1444,
						"y": 1527,
						"w": 1522,
						"h": 506
					},
					"anchor": {
						"x": 0.23051037577117217,
						"y": 0.21913043478260869
					}
				},
				{
					"filename": "arm_uzi_002.png",
					"rotated": false,
					"trimmed": true,
					"sourceSize": {
						"w": 1783,
						"h": 575
					},
					"spriteSourceSize": {
						"x": 154,
						"y": 55,
						"w": 1519,
						"h": 506
					},
					"frame": {
						"x": 1,
						"y": 2035,
						"w": 1519,
						"h": 506
					},
					"anchor": {
						"x": 0.22826696578799777,
						"y": 0.21739130434782608
					}
				},
				{
					"filename": "arm_uzi_007.png",
					"rotated": false,
					"trimmed": true,
					"sourceSize": {
						"w": 1783,
						"h": 575
					},
					"spriteSourceSize": {
						"x": 138,
						"y": 59,
						"w": 1480,
						"h": 506
					},
					"frame": {
						"x": 1522,
						"y": 2035,
						"w": 1480,
						"h": 506
					},
					"anchor": {
						"x": 0.22658440830061694,
						"y": 0.23652173913043478
					}
				}
			]
		}
	],
	"meta": {
		"app": "https://www.codeandweb.com/texturepacker",
		"version": "3.0",
		"smartupdate": "$TexturePacker:SmartUpdate:58ca21522baddadb3dce90b5f8cdf003:0a3f6278749406b6029fa175f48e7602:f7556fcd8365dae58100ed881e38b14a$"
	}
}
